{
	"backtraceGraph" : 
	{
		"commands" : 
		[
			"install"
		],
		"files" : 
		[
			"Scene/tinyobjloader/CMakeLists.txt"
		],
		"nodes" : 
		[
			{
				"file" : 0
			},
			{
				"command" : 0,
				"file" : 0,
				"line" : 118,
				"parent" : 0
			},
			{
				"command" : 0,
				"file" : 0,
				"line" : 128,
				"parent" : 0
			},
			{
				"command" : 0,
				"file" : 0,
				"line" : 135,
				"parent" : 0
			},
			{
				"command" : 0,
				"file" : 0,
				"line" : 140,
				"parent" : 0
			},
			{
				"command" : 0,
				"file" : 0,
				"line" : 145,
				"parent" : 0
			},
			{
				"command" : 0,
				"file" : 0,
				"line" : 151,
				"parent" : 0
			}
		]
	},
	"installers" : 
	[
		{
			"backtrace" : 1,
			"component" : "Unspecified",
			"destination" : "lib",
			"paths" : 
			[
				"Scene/tinyobjloader/Release/tinyobjloader.lib"
			],
			"targetId" : "tinyobjloader::@2820d806601e0aed34a9",
			"targetIndex" : 4,
			"type" : "target"
		},
		{
			"backtrace" : 2,
			"component" : "Unspecified",
			"destination" : "lib/tinyobjloader/cmake",
			"exportName" : "tinyobjloader-targets",
			"exportTargets" : 
			[
				{
					"id" : "tinyobjloader::@2820d806601e0aed34a9",
					"index" : 4
				}
			],
			"paths" : 
			[
				"Scene/tinyobjloader/CMakeFiles/Export/lib/tinyobjloader/cmake/tinyobjloader-targets.cmake"
			],
			"type" : "export"
		},
		{
			"backtrace" : 3,
			"component" : "Unspecified",
			"destination" : "include",
			"paths" : 
			[
				"Scene/tinyobjloader/tiny_obj_loader.h"
			],
			"type" : "file"
		},
		{
			"backtrace" : 4,
			"component" : "Unspecified",
			"destination" : "share/doc/tinyobjloader",
			"paths" : 
			[
				"Scene/tinyobjloader/LICENSE"
			],
			"type" : "file"
		},
		{
			"backtrace" : 5,
			"component" : "Unspecified",
			"destination" : "lib/tinyobjloader/cmake",
			"paths" : 
			[
				"build/Scene/tinyobjloader/tinyobjloader-config.cmake",
				"build/Scene/tinyobjloader/tinyobjloader-config-version.cmake"
			],
			"type" : "file"
		},
		{
			"backtrace" : 6,
			"component" : "Unspecified",
			"destination" : "lib/pkgconfig",
			"paths" : 
			[
				"build/Scene/tinyobjloader/tinyobjloader.pc"
			],
			"type" : "file"
		}
	],
	"paths" : 
	{
		"build" : "Scene/tinyobjloader",
		"source" : "Scene/tinyobjloader"
	}
}
